pydanticprotobuf/__init__.py
pydanticprotobuf/main.py
pydanticprotobuf/py.typed
pydanticprotobuf-0.2.0.dist-info/LICENSE
pydanticprotobuf-0.2.0.dist-info/WHEEL
pydanticprotobuf-0.2.0.dist-info/METADATA
pydanticprotobuf-0.2.0.dist-info/RECORD
