Metadata-Version: 2.1
Name: pydanticprotobuf
Version: 0.2.0
Summary: pydanticprotobuf
Author-email: Anthony Corletti <anthcor@gmail.com>
Requires-Python: >=3.10.8
Requires-Dist: pydantic >=1.9.0
Requires-Dist: protobuf <4.0.0
Requires-Dist: mypy >=0.910 ; extra == "dev"
Requires-Dist: mypy-protobuf >=3.0.0 ; extra == "dev"
Requires-Dist: flake8 >=3.9.2 ; extra == "dev"
Requires-Dist: black >=22.1.0 ; extra == "dev"
Requires-Dist: isort >=5.9.3 ; extra == "dev"
Requires-Dist: autoflake >=1.4 ; extra == "dev"
Requires-Dist: flake8-docstrings >=1.6.0 ; extra == "dev"
Requires-Dist: types-protobuf >=3.19.12 ; extra == "dev"
Requires-Dist: grpcio-tools >=1.46.0 ; extra == "dev"
Requires-Dist: pre-commit >=2.19.0 ; extra == "dev"
Requires-Dist: pytest >=6.2.5 ; extra == "test"
Requires-Dist: coverage >=6.1.1 ; extra == "test"
Requires-Dist: pytest-cov >=3.0.0 ; extra == "test"
Project-URL: Documentation, https://www.github.com/anthonycorletti/pydanticprotobuf
Provides-Extra: dev
Provides-Extra: test
